strf_hint/__init__.py
strf_hint/recognizer.py
strf_hint/strf_codes.py
strf_hint-0.10.dist-info/LICENSE
strf_hint-0.10.dist-info/METADATA
strf_hint-0.10.dist-info/WHEEL
strf_hint-0.10.dist-info/top_level.txt
strf_hint-0.10.dist-info/RECORD
