Metadata-Version: 2.1
Name: strf_hint
Version: 0.10
Summary: Encrypt your own datetime format using strf codes
Home-page: https://github.com/marataj/strf_hint
Author: marataj
License: MIT
License-File: LICENSE
